{
  "collectedAt": "2026-07-04",
  "items": [
    {"score":99,"articleDate":"2026-07-03","category":"방산·항공우주","keyword":"한화 국방 AI 데이터센터 10조","title":"[속보] 한화 김동관 \"창원 국방 AI 데이터센터 건설에 10조 투자\"","url":"https://www.hankyung.com/article/2026070344727"},
    {"score":98,"articleDate":"2026-07-03","category":"배터리·소재","keyword":"삼성SDI 세계최초 전고체 배터리 16조","title":"[속보] 삼성 \"울산에 16조 투자…세계 최초 전고체 배터리 양산 목표\"","url":"https://www.hankyung.com/article/2026070345237"},
    {"score":96,"articleDate":"2026-07-03","category":"AI·반도체","keyword":"앤트로픽 삼성 2나노 AI칩","title":"앤트로픽, 삼성전자와 AI 칩 생산 논의…2나노 경쟁력 시험대","url":"https://www.hani.co.kr/arti/economy/it/1266552.html"},
    {"score":94,"articleDate":"2026-07-03","category":"AI·반도체","keyword":"TSMC 병목 삼성 파운드리 빅테크 수주","title":"'TSMC 공급 병목'에 삼성 파운드리 기회…빅테크 고객 확 늘듯","url":"https://www.mk.co.kr/news/business/12090115"},
    {"score":93,"articleDate":"2026-07-03","category":"자동차·로봇","keyword":"현대차 영남 42조 레벨4 자율주행","title":"현대차그룹, 영남권에 42조원 투자… 'AI 자율주행·항공' 거점 키운다","url":"https://www.etnews.com/20260703000273"},
    {"score":91,"articleDate":"2026-07-03","category":"원전·SMR","keyword":"세계최초 SMR 전용공장 창원","title":"SMR 전용 공장 짓는 두산…稅혜택 가장 많이 받을 듯","url":"https://www.hankyung.com/amp/2026070349761"},
    {"score":89,"articleDate":"2026-07-03","category":"방산·항공우주","keyword":"NATO 방산협력 드론 우주 공동개발","title":"李대통령 내주 나토 정상회의 참석…“방산협력 본격 추진”","url":"https://www.donga.com/news/Politics/article/all/20260703/134229951/1"},
    {"score":87,"articleDate":"2026-07-03","category":"AI·반도체","keyword":"삼성전기 AI 반도체 부품 풀라인업","title":"장덕현 '공급망 내재화' 승부수···삼성전기, AI 반도체 부품 '풀라인업' 구축","url":"https://www.newsway.co.kr/news/view?ud=2026070314291262110"},
    {"score":85,"articleDate":"2026-07-03","category":"방산·항공우주","keyword":"한국형 저궤도 위성통신망 2035","title":"[속보] 우주청장 \"한국형 저궤도 위성통신망 2035년까지 완성\"","url":"https://www.hankyung.com/article/2026070345877"},
    {"score":83,"articleDate":"2026-07-03","category":"방산·항공우주","keyword":"남해안 우주항공 벨트 국가 지원","title":"이 대통령 \"남해안 우주항공 벨트 우주 강국 선도할 거라 믿어…아낌없이 지원\"","url":"https://nwww.newsis.com/view/NISX20260703_0003695145"},
    {"score":80,"articleDate":"2026-07-03","category":"조선·중공업","keyword":"K조선 역대급 실적 캐나다 잠수함","title":"실적은 역대급인데 주가는 급락…롤러코스터 탄 '조선주'","url":"https://www.hankyung.com/article/202607034411i"},
    {"score":77,"articleDate":"2026-07-03","category":"AI·반도체","keyword":"삼성전자 HBM 경쟁력 SK하이닉스 공급부족","title":"\"59만전자·420만닉스 간다\" 반도체 쌍두마차, 메타발 폭락 뒤 목표가↑... LG전자도 '깜짝 실적' 예고 [株토피아]","url":"https://www.fnnews.com/news/202607031040504031"}
  ]
}
